dockerized/__init__.py
dockerized/adapters/__init__.py
dockerized/adapters/dockercompose.py
dockerized/adapters/environment.py
dockerized/adapters/test_dockercompose.py
dockerized/core/__init__.py
dockerized/core/commands/__init__.py
dockerized/core/commands/clean.py
dockerized/core/commands/compose.py
dockerized/core/commands/dockercomposecommand.py
dockerized/core/commands/errors.py
dockerized/core/commands/exec.py
dockerized/core/commands/init.py
dockerized/core/commands/push.py
dockerized/core/commands/shell.py
dockerized/core/commands/test_clean.py
dockerized/core/commands/test_compose.py
dockerized/core/commands/test_init.py
dockerized/core/commands/test_push.py
dockerized/core/commands/test_shell.py
dockerized/core/commands/version.py
dockerized/core/config.py
dockerized/core/errors.py
dockerized/core/project.py
dockerized/core/test_project.py
dockerized/test/__init__.py
dockerized/ui/__init__.py
dockerized/ui/cli.py
dockerized/version.py
dockerized-0.21.0.dist-info/LICENSE
dockerized-0.21.0.dist-info/METADATA
dockerized-0.21.0.dist-info/WHEEL
dockerized-0.21.0.dist-info/entry_points.txt
dockerized-0.21.0.dist-info/RECORD
