Metadata-Version: 2.1
Name: dockerized
Version: 0.21.0
Summary: Seamlessly execute commands in a container
License: MIT
Author: Itamar Ben-Zaken
Author-email: benzaita@gmail.com
Requires-Python: >=3.10,<4.0
Classifier: License :: OSI Approved :: MIT License
Classifier: Programming Language :: Python :: 3
Classifier: Programming Language :: Python :: 3.10
Classifier: Programming Language :: Python :: 3.11
Classifier: Programming Language :: Python :: 3.12
Requires-Dist: click (>=7.1.2,<8.0.0)
Requires-Dist: pyyaml (>=6.0.1,<7.0.0)
